nonmin_pose-0.0.1.dist-info/RECORD
nonmin_pose-0.0.1.dist-info/WHEEL
nonmin_pose-0.0.1.dist-info/LICENSE
nonmin_pose-0.0.1.dist-info/METADATA
nonmin_pose-0.0.1.dist-info/top_level.txt
nonmin_pose/__init__.py
nonmin_pose/utils.py
nonmin_pose/sdpa.pypy37-pp73-x86_64-linux-gnu.so
nonmin_pose/sdp_zhao.pypy37-pp73-x86_64-linux-gnu.so
nonmin_pose/models/essential_mat_gsalguero.py
nonmin_pose/models/base.py
nonmin_pose/models/essential_mat_zhao.py
nonmin_pose/models/c2p.py
nonmin_pose/constraints/constraint_manager.py
nonmin_pose/constraints/constraints.py
nonmin_pose.libs/libquadmath-96973f99.so.0.0.0
nonmin_pose.libs/libgfortran-040039e1.so.5.0.0
nonmin_pose.libs/libopenblas-r0-f650aae0.3.3.so
nonmin_pose.libs/libgomp-a34b3233.so.1.0.0
nonmin_pose.libs/libgfortran-91cc3cb1.so.3.0.0
