Metadata-Version: 2.1
Name: nonmin-pose
Version: 0.0.1
Summary: Code corresponding to the paper 'From Correspondences to Pose: Non-minimal Certifiably Optimal Relative Pose without Disambiguation'
Author-email: Javier Tirado Garin <jtiradogarin@gmail.com>
License:                     GNU GENERAL PUBLIC LICENSE
Project-URL: Homepage, https://github.com/javrtg/C2P
Project-URL: Bug Tracker, https://github.com/javrtg/C2P/issues
Requires-Python: >=3.7
License-File: LICENSE
Requires-Dist: numpy
